pyalab/__init__.py
pyalab/constants.py
pyalab/deck.py
pyalab/integra_xml.py
pyalab/pipette.py
pyalab/plate.py
pyalab/program.py
pyalab/py.typed
pyalab/steps/__init__.py
pyalab/steps/base.py
pyalab/steps/builders.py
pyalab/steps/multi_dispense.py
pyalab/steps/params.py
pyalab/steps/set_volume.py
pyalab/steps/transfer.py
pyalab/vendor_files/integra_library/Deck/3 Position Universal Deck V12.xml
pyalab/vendor_files/integra_library/Deck/4 Position Portrait Deck V02.xml
pyalab/vendor_files/integra_library/FlexBase/ALPAQUA 96S Super Magnet Plate V02.xml
pyalab/vendor_files/integra_library/FlexBase/INHECO CPAC Ultraflat Base V01.xml
pyalab/vendor_files/integra_library/FlexBase/INHECO CPAC Ultraflat Dual Reservoir Adapter for 2 x 25 ml or 2 x Divided Reagent Reservoirs V02.xml
pyalab/vendor_files/integra_library/FlexBase/INHECO CPAC Ultraflat F-bottom Adapter V02.xml
pyalab/vendor_files/integra_library/FlexBase/INHECO CPAC Ultraflat PCR Plate Adapter V02.xml
pyalab/vendor_files/integra_library/FlexBase/INHECO CPAC Ultraflat with Dual Reservoir Adapter for 2 x 10 ml Reservoirs V00.xml
pyalab/vendor_files/integra_library/FlexBase/INHECO HeatPAC F-bottom Adapter V02.xml
pyalab/vendor_files/integra_library/FlexBase/INHECO HeatPAC PCR Plate Adapter V02.xml
pyalab/vendor_files/integra_library/FlexBase/INHECO HeatPAC no Adapter V00.xml
pyalab/vendor_files/integra_library/FlexBase/INHECO HeatPAC with Dual Reservoir Adapter for 2 x 25ml or 2 x Divided Reagent Reservoirs V02.xml
pyalab/vendor_files/integra_library/FlexBase/INHECO HeatPAC with Dual Reservoir Adapter for 2x10ml Reservoirs V02.xml
pyalab/vendor_files/integra_library/FlexBase/INHECO Teleshake 95 F-bottom Adapter V02.xml
pyalab/vendor_files/integra_library/FlexBase/INHECO Teleshake 95 no Adapter V00.xml
pyalab/vendor_files/integra_library/FlexBase/INHECO Teleshake no Adapter V00.xml
pyalab/vendor_files/integra_library/FlexBase/INTEGRA Dual Reservoir Adapter V03.xml
pyalab-0.2.6.dist-info/METADATA
pyalab-0.2.6.dist-info/WHEEL
pyalab-0.2.6.dist-info/top_level.txt
pyalab-0.2.6.dist-info/RECORD
