Metadata-Version: 2.4
Name: pyalab
Version: 0.2.6
Summary: Generating programs for Vialab to control an Integra Assist Plus liquid handling robot
Author: Eli Fine
Classifier: Programming Language :: Python :: 3
Classifier: Programming Language :: Python :: 3.12
Classifier: Programming Language :: Python :: 3.13
Requires-Python: >=3.12.7
Requires-Dist: pydantic>=2.10.3
Requires-Dist: inflection>=0.5.1
Requires-Dist: lxml>=6.0.0
